{
  "unversionedId": "roles/integrator/implicit-accounts",
  "id": "roles/integrator/implicit-accounts",
  "isDocsHomePage": false,
  "title": "Implicit Accounts",
  "description": "Background",
  "source": "@site/../docs/roles/integrator/implicit-accounts.md",
  "sourceDirName": "roles/integrator",
  "slug": "/roles/integrator/implicit-accounts",
  "permalink": "/docs/roles/integrator/implicit-accounts",
  "editUrl": "https://github.com/near/docs/tree/master/docs/../docs/roles/integrator/implicit-accounts.md",
  "version": "current",
  "lastUpdatedBy": "Author",
  "lastUpdatedAt": 1539502055,
  "formattedLastUpdatedAt": "10/14/2018",
  "sidebar_label": "Implicit Accounts",
  "frontMatter": {
    "id": "implicit-accounts",
    "title": "Implicit Accounts",
    "sidebar_label": "Implicit Accounts"
  },
  "sidebar": "integrate",
  "previous": {
    "title": "Exchange Integration",
    "permalink": "/docs/roles/integrator/exchange-integration"
  },
  "next": {
    "title": "Introduction",
    "permalink": "/docs/roles/integrator/errors/introduction"
  }
}